gptstonks/multiagents/__init__.py
gptstonks/multiagents/graphs/__init__.py
gptstonks/multiagents/graphs/agent_with_tools.py
gptstonks/multiagents/states/__init__.py
gptstonks/multiagents/states/base.py
gptstonks/multiagents/tools/__init__.py
gptstonks/multiagents/tools/ddg_results_json.py
gptstonks/multiagents/tools/mitheithel_search.py
gptstonks/multiagents/tools/world_knowledge.py
gptstonks/multiagents/tools/youtube_search.py
gptstonks_multiagents-0.0.3.dist-info/METADATA
gptstonks_multiagents-0.0.3.dist-info/WHEEL
gptstonks_multiagents-0.0.3.dist-info/entry_points.txt
gptstonks_multiagents-0.0.3.dist-info/RECORD
