Metadata-Version: 2.1
Name: gptstonks-multiagents
Version: 0.0.3
Summary: Multi-Agent architectures to create copilots and autopilots.
Author-Email: GPTStonks Team <hello@gptstonks.net>
License: MIT
Classifier: Programming Language :: Python :: 3
Classifier: License :: OSI Approved :: MIT License
Classifier: Operating System :: OS Independent
Project-URL: Homepage, https://github.com/GPTStonks/gptstonks
Project-URL: Bug Tracker, https://github.com/GPTStonks/gptstonks/issues
Requires-Python: <3.11,>=3.10
Requires-Dist: gptstonks-wrappers>=0.0.3.post1
Requires-Dist: langgraph<0.3,>=0.2.20
Requires-Dist: langchain<0.4,>=0.3
Requires-Dist: asyncio>=3.4.3
Requires-Dist: llama-index>=0.10.30
Requires-Dist: duckduckgo-search>=5.3.0
Requires-Dist: wikipedia>=1.4.0
Requires-Dist: llama-index-llms-openai>=0.1.16
Requires-Dist: langchain-community<0.4,>=0.3
Requires-Dist: websockets>=14.1
Provides-Extra: testing
Requires-Dist: pytest; extra == "testing"
Requires-Dist: pytest-cov; extra == "testing"
Requires-Dist: trio>=0.23.2; extra == "testing"
Requires-Dist: pytest-asyncio>=0.23.5; extra == "testing"
